LICENSE
README.md
demo-ca.sh
demo-cca.sh
demo-pca.sh
demo.sh
gen-mat.py
setup.py
delayedsparse/__init__.py
delayedsparse/__version__.py
delayedsparse/ca.py
delayedsparse/cca.py
delayedsparse/delayedsparse.py
delayedsparse/extmath2.py
delayedsparse/pca.py
delayedsparse.egg-info/PKG-INFO
delayedsparse.egg-info/SOURCES.txt
delayedsparse.egg-info/dependency_links.txt
delayedsparse.egg-info/requires.txt
delayedsparse.egg-info/top_level.txt