Metadata-Version: 1.2
Name: delayedsparse
Version: 0.2.4
Summary: Delayed sparse matrix in Python
Home-page: https://github.com/niitsuma/delayedsparse
Author: Hirotaka Niitsuma
Author-email: hirotaka.niitsuma@gmail.com
License: You can use these codes olny for self evaluation. Cannot use these codes for commercial and academical use.
Platform: UNKNOWN
Classifier: Programming Language :: Python :: 3
Classifier: Programming Language :: Python :: 3.4
Classifier: Programming Language :: Python :: 3.5
Classifier: Programming Language :: Python :: 3.6
Classifier: Topic :: Scientific/Engineering :: Mathematics
Requires-Python: >=3.4.0
